pyicloud/__init__.py
pyicloud/base.py
pyicloud/cmdline.py
pyicloud/exceptions.py
pyicloud/services/__init__.py
pyicloud/services/account.py
pyicloud/services/calendar.py
pyicloud/services/contacts.py
pyicloud/services/drive.py
pyicloud/services/findmyiphone.py
pyicloud/services/photos.py
pyicloud/services/reminders.py
pyicloud/services/ubiquity.py
pyicloud/utils.py
pyicloud_z-0.9.7b2.dist-info/LICENSE.txt
pyicloud_z-0.9.7b2.dist-info/WHEEL
pyicloud_z-0.9.7b2.dist-info/METADATA
pyicloud_z-0.9.7b2.dist-info/RECORD
