Metadata-Version: 2.1
Name: pyicloud-z
Version: 0.9.7b2
Summary: 
Author: Your Name
Author-email: you@example.com
Requires-Python: >=3.6,<4.0
Classifier: Programming Language :: Python :: 3
Classifier: Programming Language :: Python :: 3.6
Classifier: Programming Language :: Python :: 3.7
Classifier: Programming Language :: Python :: 3.8
Requires-Dist: certifi (>=2019.11.28)
Requires-Dist: click (>=6.0,<=7.1.1)
Requires-Dist: future (>=0.18.2)
Requires-Dist: keyring (>=8.0,<=9.3.1)
Requires-Dist: keyrings.alt (>=1.0,<=3.2.0)
Requires-Dist: pytz (>=2019.3)
Requires-Dist: requests (>=2.20.0)
Requires-Dist: six (>=1.14.0)
Requires-Dist: tzlocal (==2.0.0)
